odoo9_addon_account_reversal-9.0.1.0.0-py2.7-nspkg.pth
odoo_addons/account_reversal/__openerp__.py
odoo_addons/account_reversal/__init__.py
odoo_addons/account_reversal/README.rst
odoo_addons/account_reversal/models/__init__.py
odoo_addons/account_reversal/models/account_move.py
odoo_addons/account_reversal/i18n/ja.po
odoo_addons/account_reversal/i18n/zh_CN.po
odoo_addons/account_reversal/i18n/ru.po
odoo_addons/account_reversal/i18n/gl_ES.po
odoo_addons/account_reversal/i18n/pt.po
odoo_addons/account_reversal/i18n/it.po
odoo_addons/account_reversal/i18n/es.po
odoo_addons/account_reversal/i18n/nl_BE.po
odoo_addons/account_reversal/i18n/ar.po
odoo_addons/account_reversal/i18n/lt.po
odoo_addons/account_reversal/i18n/ro.po
odoo_addons/account_reversal/i18n/tr.po
odoo_addons/account_reversal/i18n/mk.po
odoo_addons/account_reversal/i18n/hr.po
odoo_addons/account_reversal/i18n/bg.po
odoo_addons/account_reversal/i18n/es_EC.po
odoo_addons/account_reversal/i18n/zh_TW.po
odoo_addons/account_reversal/i18n/hu.po
odoo_addons/account_reversal/i18n/gl.po
odoo_addons/account_reversal/i18n/ca.po
odoo_addons/account_reversal/i18n/es_CR.po
odoo_addons/account_reversal/i18n/sl.po
odoo_addons/account_reversal/i18n/sr@latin.po
odoo_addons/account_reversal/i18n/th.po
odoo_addons/account_reversal/i18n/es_ES.po
odoo_addons/account_reversal/i18n/cs.po
odoo_addons/account_reversal/i18n/pt_PT.po
odoo_addons/account_reversal/i18n/ca_ES.po
odoo_addons/account_reversal/i18n/nb.po
odoo_addons/account_reversal/i18n/et.po
odoo_addons/account_reversal/i18n/mn.po
odoo_addons/account_reversal/i18n/nl.po
odoo_addons/account_reversal/i18n/am.po
odoo_addons/account_reversal/i18n/account_reversal.pot
odoo_addons/account_reversal/i18n/de.po
odoo_addons/account_reversal/i18n/vi.po
odoo_addons/account_reversal/i18n/fr.po
odoo_addons/account_reversal/i18n/pl.po
odoo_addons/account_reversal/i18n/bs.po
odoo_addons/account_reversal/i18n/pt_BR.po
odoo9_addon_account_reversal-9.0.1.0.0.dist-info/top_level.txt
odoo9_addon_account_reversal-9.0.1.0.0.dist-info/WHEEL
odoo9_addon_account_reversal-9.0.1.0.0.dist-info/RECORD
odoo9_addon_account_reversal-9.0.1.0.0.dist-info/metadata.json
odoo9_addon_account_reversal-9.0.1.0.0.dist-info/DESCRIPTION.rst
odoo9_addon_account_reversal-9.0.1.0.0.dist-info/METADATA
odoo9_addon_account_reversal-9.0.1.0.0.dist-info/namespace_packages.txt
